LICENSE
MANIFEST.in
setup.py
image_ui/__init__.py
image_ui/admin.py
image_ui/conf.py
image_ui/static/image_ui/colorbox/README.md
image_ui/static/image_ui/colorbox/colorbox.ai
image_ui/static/image_ui/colorbox/colorbox.css
image_ui/static/image_ui/colorbox/colorbox.jquery.json
image_ui/static/image_ui/colorbox/component.json
image_ui/static/image_ui/colorbox/jquery.colorbox-min.js
image_ui/static/image_ui/colorbox/jquery.colorbox.js
image_ui/static/image_ui/colorbox/i18n/jquery.colorbox-cs.js
image_ui/static/image_ui/colorbox/i18n/jquery.colorbox-da.js
image_ui/static/image_ui/colorbox/i18n/jquery.colorbox-de.js
image_ui/static/image_ui/colorbox/i18n/jquery.colorbox-es.js
image_ui/static/image_ui/colorbox/i18n/jquery.colorbox-fr.js
image_ui/static/image_ui/colorbox/i18n/jquery.colorbox-it.js
image_ui/static/image_ui/colorbox/i18n/jquery.colorbox-kr.js
image_ui/static/image_ui/colorbox/i18n/jquery.colorbox-nl.js
image_ui/static/image_ui/colorbox/i18n/jquery.colorbox-pl.js
image_ui/static/image_ui/colorbox/i18n/jquery.colorbox-pt-br.js
image_ui/static/image_ui/colorbox/i18n/jquery.colorbox-ru.js
image_ui/static/image_ui/colorbox/images/border.png
image_ui/static/image_ui/colorbox/images/controls.png
image_ui/static/image_ui/colorbox/images/loading.gif
image_ui/static/image_ui/colorbox/images/loading_background.png
image_ui/static/image_ui/colorbox/images/overlay.png
image_ui/static/image_ui/colorbox/images/ie6/borderBottomCenter.png
image_ui/static/image_ui/colorbox/images/ie6/borderBottomLeft.png
image_ui/static/image_ui/colorbox/images/ie6/borderBottomRight.png
image_ui/static/image_ui/colorbox/images/ie6/borderMiddleLeft.png
image_ui/static/image_ui/colorbox/images/ie6/borderMiddleRight.png
image_ui/static/image_ui/colorbox/images/ie6/borderTopCenter.png
image_ui/static/image_ui/colorbox/images/ie6/borderTopLeft.png
image_ui/static/image_ui/colorbox/images/ie6/borderTopRight.png
image_ui/static/image_ui/js/admin-list-reorder.js
twentytab_image_ui.egg-info/PKG-INFO
twentytab_image_ui.egg-info/SOURCES.txt
twentytab_image_ui.egg-info/dependency_links.txt
twentytab_image_ui.egg-info/requires.txt
twentytab_image_ui.egg-info/top_level.txt