Metadata-Version: 1.0
Name: twentytab-image-ui
Version: 0.5
Summary: A django app that implements an admin to have thumbnails with colorbox.js
Home-page: https://github.com/20tab/twentytab-image-ui
Author: 20tab S.r.l.
Author-email: info@20tab.com
License: MIT License
Platform: UNKNOWN
